{
  "526": "100.0,1,1,false",
  "199": "88.0,1,1,false",
  "201": "78.0,1,1,false",
  "203": "91.0,1,1,false",
  "205": "49.0,1,1,false",
  "207": "32.0,1,1,false",
  "209": "55.0,1,1,false",
  "211": "61.0,1,1,false",
  "213": "36.0,1,1,false",
  "215": "6.0,1,1,false",
  "2485": "6.0,1,1,false",
  "217": "4.0,1,1,false",
  "1351": "59.0,1,1,false",
  "1291": "62.0,1,1,false",
  "1139": "74.0,1,1,false",
  "1189": "71.0,1,1,false",
  "1203": "59.0,1,1,false",
  "1349": "71.0,1,1,false",
  "1420": "98.0,1,1,false",
  "884": "63.0,5,8,false",
  "886": "97.0,5,32,false",
  "888": "68.0,1,2,false",
  "830": "40.0,5,5,false",
  "2366": "2.0,1,1,false",
  "19830": "65.0,1,1,false",
  "1623": "54.0,1,1,false",
  "1621": "27.0,1,1,false",
  "1619": "35.0,1,1,false",
  "1617": "8.0,1,1,false",
  "1631": "58.0,1,1,false",
  "562": "72.0,4,4,false",
  "556": "60.0,3,3,false",
  "554": "73.0,3,7,false",
  "558": "58.0,3,5,false",
  "559": "65.0,3,3,false",
  "561": "31.0,5,5,false",
  "563": "63.0,2,2,false",
  "564": "68.0,2,2,false",
  "1462": "1.0,1,1,false",
  "3420": "84.0,2,2,false",
  "6476": "75.0,1,1,false",
  "995": "84.0,1,1,false",
  "313": "95.0,1,9,false",
  "29": "61.0,1,1,false",
  "1917": "74.0,1,1,false",
  "436": "67.0,1,1,false",
  "441": "67.0,6,6,false",
  "438": "61.0,1,1,false",
  "592": "65.0,1,1,false",
  "221": "61.0,1,1,false",
  "2331": "8.0,1,1,false",
  "987": "27.0,1,1,false",
  "0": "0,0,0,false"
}