{
  "444": "98.0,1,1,false",
  "442": "77.0,1,1,false",
  "1761": "85.0,3,3,false",
  "2353": "68.0,1,1,false",
  "1623": "71.0,1,1,false",
  "1621": "65.0,1,1,false",
  "1619": "55.0,1,1,false",
  "1617": "62.0,1,1,false",
  "9194": "38.0,1,1,false",
  "1775": "97.0,2,2,false",
  "1391": "74.0,1,1,false",
  "1743": "84.0,1,1,false",
  "1741": "85.0,3,3,false",
  "1737": "83.0,8,8,false",
  "1780": "91.0,5,8,false",
  "7937": "99.0,4,8,false",
  "379": "90.0,1,1,false",
  "149": "1.0,1,1,false",
  "161": "1.0,1,1,false"
}