{
  "536": "100.0,1,1,false",
  "1747": "100.0,1,1,false",
  "1315": "99.0,1,1,false",
  "1361": "60.0,1,1,false",
  "1369": "63.0,1,1,false",
  "1355": "61.0,1,1,false",
  "1303": "60.0,1,1,false",
  "1319": "6.0,1,1,false",
  "1373": "8.0,1,1,false",
  "1247": "7.0,1,1,false",
  "1249": "1.0,1,1,false",
  "1215": "4.0,1,1,false",
  "1197": "59.0,1,1,false",
  "1123": "58.0,1,1,false",
  "1185": "74.0,1,1,false",
  "1201": "6.0,1,1,false",
  "1149": "5.0,1,1,false",
  "816": "87.0,16,16,false",
  "829": "79.0,30,30,false",
  "868": "67.0,2,2,false",
  "811": "74.0,10,10,false",
  "892": "2.0,42,150,false",
  "830": "8.0,5,5,false",
  "886": "7.0,150,150,false",
  "556": "70.0,75,75,false",
  "565": "58.0,15,15,false",
  "560": "58.0,5,15,false",
  "554": "71.0,50,50,false",
  "563": "73.0,10,45,false",
  "561": "72.0,67,67,false",
  "562": "63.0,90,90,false",
  "1452": "65.0,1,1,false",
  "1462": "2.0,1,1,false",
  "1623": "67.0,1,1,false",
  "1621": "62.0,1,1,false",
  "1619": "73.0,1,1,false",
  "1617": "69.0,1,1,false",
  "526": "50.0,1,1,false",
  "1615": "62.0,1,1,false",
  "443": "8.0,100,100,false",
  "618": "87.0,1,176,false",
  "1897": "68.0,1,1,false",
  "987": "30.0,1,1,false",
  "985": "31.0,1,1,false",
  "2366": "1.0,1,1,false",
  "11286": "8.0,1,1,false",
  "0": "0,0,0,false"
}