{
  "526": "100.0,1,1,false",
  "557": "85.0,1,1,false",
  "555": "81.0,1,1,false",
  "4698": "59.0,1,1,false",
  "564": "1.0,1,1,false",
  "561": "1.0,1,1,false",
  "560": "1.0,50,50,false",
  "830": "43.0,5,5,false",
  "1249": "39.0,1,1,false",
  "199": "76.0,1,1,false",
  "201": "81.0,1,1,false",
  "207": "70.0,1,1,false",
  "203": "81.0,1,1,false",
  "205": "90.0,1,1,false",
  "209": "58.0,1,1,false",
  "14836": "56.0,1,1,false",
  "213": "69.0,1,1,false",
  "2485": "74.0,1,1,false",
  "217": "57.0,1,1,false",
  "215": "42.0,1,1,false",
  "211": "39.0,1,1,false",
  "10978": "75.0,1,1,false",
  "14870": "69.0,1,1,false",
  "995": "1.0,1,1,false",
  "1623": "57.0,1,1,false",
  "1621": "59.0,1,1,false",
  "1619": "60.0,1,1,false",
  "1617": "54.0,1,1,false",
  "1462": "54.0,1,1,false",
  "987": "53.0,1,1,false",
  "985": "32.0,1,1,false",
  "7416": "38.0,1,1,false",
  "2366": "7.0,1,1,false",
  "0": "0,0,0,false"
}