{
  "556": "80.0,10,10,false",
  "557": "85.0,9,9,false",
  "554": "97.0,5,5,false",
  "562": "99.0,2,2,false",
  "561": "99.0,2,2,false",
  "563": "59.0,2,2,false",
  "565": "5.0,1,1,false",
  "1321": "98.0,1,1,false",
  "882": "76.0,1,9,false",
  "1203": "87.0,1,1,false",
  "1115": "35.0,1,1,false",
  "9140": "86.0,1,2,false",
  "1241": "76.0,1,1,false",
  "830": "91.0,5,5,false",
  "1381": "65.0,1,1,false",
  "877": "78.0,1,2,false",
  "1623": "27.0,1,1,false",
  "1621": "52.0,1,1,false",
  "1619": "52.0,1,1,false",
  "1617": "8.0,1,1,false",
  "526": "50.0,1,1,false",
  "618": "84.0,1,4,false",
  "1025": "80.0,1,1,false",
  "2351": "44.0,2,2,false",
  "0": "0,0,0,false",
  "987": "2.0,1,1,false",
  "985": "9.0,1,1,false",
  "225": "6.0,1,1,false",
  "1462": "56.0,1,1,false",
  "1452": "61.0,1,1,false",
  "29": "83.0,1,1,false",
  "946": "1.0,1,1,false"
}