{
  "526": "100.0,1,1,false",
  "199": "83.0,1,1,false",
  "201": "88.0,1,1,false",
  "203": "97.0,1,1,false",
  "205": "36.0,1,1,false",
  "207": "33.0,1,1,false",
  "209": "64.0,1,1,false",
  "211": "72.0,1,1,false",
  "213": "30.0,1,1,false",
  "215": "74.0,1,1,false",
  "2485": "7.0,1,1,false",
  "217": "7.0,1,1,false",
  "1351": "73.0,1,1,false",
  "1291": "56.0,1,1,false",
  "1139": "73.0,1,1,false",
  "1189": "69.0,1,1,false",
  "1203": "67.0,1,1,false",
  "1349": "70.0,1,1,false",
  "1420": "86.0,1,1,false",
  "884": "70.0,5,8,false",
  "886": "92.0,5,32,false",
  "888": "67.0,1,2,false",
  "830": "40.0,5,5,false",
  "2366": "2.0,1,1,false",
  "19830": "61.0,1,1,false",
  "1623": "26.0,1,1,false",
  "1621": "39.0,1,1,false",
  "1619": "34.0,1,1,false",
  "1617": "5.0,1,1,false",
  "1631": "4.0,1,1,false",
  "562": "71.0,4,4,false",
  "556": "59.0,3,3,false",
  "554": "70.0,3,7,false",
  "558": "69.0,3,5,false",
  "559": "66.0,3,3,false",
  "561": "33.0,5,5,false",
  "563": "57.0,2,2,false",
  "564": "57.0,2,2,false",
  "1462": "3.0,1,1,false",
  "3420": "81.0,2,2,false",
  "6476": "89.0,1,1,false",
  "995": "75.0,1,1,false",
  "313": "90.0,1,9,false",
  "29": "63.0,1,1,false",
  "1917": "55.0,1,1,false",
  "436": "69.0,1,1,false",
  "441": "65.0,6,6,false",
  "438": "57.0,1,1,false",
  "592": "59.0,1,1,false",
  "221": "55.0,1,1,false",
  "2331": "3.0,1,1,false",
  "987": "25.0,1,1,false",
  "0": "0,0,0,false"
}