{
  "526": "100.0,1,1,false",
  "199": "76.0,1,1,false",
  "201": "80.0,1,1,false",
  "203": "98.0,1,1,false",
  "205": "33.0,1,1,false",
  "207": "49.0,1,1,false",
  "209": "71.0,1,1,false",
  "211": "56.0,1,1,false",
  "213": "37.0,1,1,false",
  "215": "4.0,1,1,false",
  "2485": "9.0,1,1,false",
  "217": "4.0,1,1,false",
  "1351": "67.0,1,1,false",
  "1291": "55.0,1,1,false",
  "1139": "60.0,1,1,false",
  "1189": "74.0,1,1,false",
  "1203": "62.0,1,1,false",
  "1349": "60.0,1,1,false",
  "1420": "78.0,1,1,false",
  "884": "58.0,5,8,false",
  "886": "75.0,5,32,false",
  "888": "68.0,1,2,false",
  "830": "44.0,5,5,false",
  "2366": "57.0,1,1,false",
  "19830": "55.0,1,1,false",
  "1623": "47.0,1,1,false",
  "1621": "43.0,1,1,false",
  "1619": "36.0,1,1,false",
  "1617": "2.0,1,1,false",
  "1631": "8.0,1,1,false",
  "562": "69.0,4,4,false",
  "556": "72.0,3,3,false",
  "554": "68.0,3,7,false",
  "558": "61.0,3,5,false",
  "559": "63.0,3,3,false",
  "561": "32.0,5,5,false",
  "563": "68.0,2,2,false",
  "564": "70.0,2,2,false",
  "1462": "4.0,1,1,false",
  "3420": "87.0,2,2,false",
  "6476": "83.0,1,1,false",
  "995": "88.0,1,1,false",
  "313": "77.0,1,9,false",
  "29": "58.0,1,1,false",
  "1917": "61.0,1,1,false",
  "436": "65.0,1,1,false",
  "441": "69.0,6,6,false",
  "438": "64.0,1,1,false",
  "592": "63.0,1,1,false",
  "221": "72.0,1,1,false",
  "2331": "6.0,1,1,false",
  "987": "36.0,1,1,false",
  "0": "0,0,0,false"
}