{
  "526": "100.0,1,1,false",
  "558": "74.0,2,9,false",
  "557": "59.0,10,10,false",
  "559": "70.0,9,9,false",
  "564": "72.0,7,7,false",
  "562": "57.0,4,6,false",
  "560": "64.0,2,2,false",
  "563": "68.0,3,4,false",
  "565": "37.0,50,50,false",
  "561": "9.0,6,6,false",
  "1452": "4.0,1,1,false",
  "5318": "67.0,4,4,false",
  "5319": "72.0,4,4,false",
  "5324": "45.0,4,4,false",
  "5322": "32.0,3,3,false",
  "5320": "41.0,3,3,false",
  "5323": "27.0,3,3,false",
  "5321": "44.0,2,2,false",
  "1279": "88.0,1,1,false",
  "1153": "95.0,1,1,false",
  "1424": "84.0,1,1,false",
  "1165": "54.0,1,1,false",
  "888": "60.0,3,3,false",
  "1313": "49.0,1,1,false",
  "1283": "33.0,1,1,false",
  "1249": "7.0,1,1,false",
  "830": "34.0,5,5,false",
  "199": "76.0,1,1,false",
  "201": "93.0,1,1,false",
  "203": "88.0,1,1,false",
  "205": "98.0,1,1,false",
  "207": "69.0,1,1,false",
  "209": "61.0,1,1,false",
  "211": "70.0,1,1,false",
  "213": "66.0,1,1,false",
  "215": "66.0,1,1,false",
  "2485": "58.0,1,1,false",
  "217": "60.0,1,1,false",
  "995": "95.0,1,1,false",
  "2353": "88.0,1,1,false",
  "1933": "93.0,1,1,false",
  "1623": "77.0,1,1,false",
  "1621": "55.0,1,1,false",
  "2309": "72.0,1,1,false",
  "438": "60.0,1,1,false",
  "1619": "40.0,1,1,false",
  "1617": "26.0,1,1,false",
  "985": "31.0,1,1,false",
  "2366": "1.0,1,1,false",
  "0": "0,0,0,false"
}