{
  "20268": "-1.0,1,1,false",
  "11710": "1524.0,1,1,false",
  "11712": "1524.0,1,1,false",
  "11714": "1524.0,1,1,false",
  "618": "76.0,1,500,false",
  "886": "67.0,95,500,false",
  "808": "72.0,96,500,false",
  "1623": "68.0,1,1,false",
  "1621": "70.0,1,1,false",
  "1619": "55.0,1,1,false",
  "985": "73.0,1,1,false",
  "987": "67.0,1,1,false",
  "565": "55.0,1,5,false",
  "560": "69.0,1,5,false",
  "7060": "56.0,2,2,false",
  "157": "63.0,1,1,false",
  "246": "55.0,1,5,false",
  "385": "58.0,2,2,false",
  "1617": "29.0,1,1,false",
  "2366": "25.0,1,1,false",
  "1149": "54.0,1,1,false",
  "11716": "5376.0,1,1,false"
}