{
  "526": "100.0,1,1,false",
  "555": "65.0,7,7,false",
  "557": "61.0,4,4,false",
  "554": "70.0,6,6,false",
  "558": "61.0,9,9,false",
  "562": "37.0,2,2,false",
  "559": "5.0,7,7,false",
  "199": "87.0,1,1,false",
  "201": "68.0,1,1,false",
  "203": "71.0,1,1,false",
  "205": "63.0,1,1,false",
  "207": "57.0,1,1,false",
  "213": "66.0,1,1,false",
  "209": "67.0,1,1,false",
  "211": "27.0,1,1,false",
  "215": "48.0,1,1,false",
  "217": "51.0,1,1,false",
  "2485": "42.0,1,1,false",
  "19830": "99.0,1,1,false",
  "877": "95.0,1,2,false",
  "882": "70.0,7,7,false",
  "1203": "57.0,1,1,false",
  "1139": "74.0,1,1,false",
  "1381": "29.0,1,1,false",
  "995": "94.0,1,1,false",
  "1438": "74.0,1,1,false",
  "1440": "64.0,1,1,false",
  "1965": "70.0,1,1,false",
  "313": "62.0,1,1,false",
  "436": "72.0,1,1,false",
  "438": "66.0,1,1,false"
}